[
  {
    "markup": "-",
    "status": true,
    "type": "internal",
    "signUpDate": 1581337765728,
    "location": "Moscow",
    "company": "Nike",
    "name": "Mr. Serhii Movchan",
    "id": "1"
  },
  {
    "markup": "-",
    "status": false,
    "type": "internal",
    "signUpDate": 1581397765728,
    "location": "Moscow",
    "company": "Nike",
    "name": "Mr. Serhii Movchan2",
    "id": "2"
  },
  {
    "markup": "-",
    "status": false,
    "type": "internal",
    "signUpDate": 1281397765728,
    "location": "Moscow",
    "company": "Nike",
    "name": "Mr. Serhii Movchan3",
    "id": "34234"
  },
  {
    "markup": "-",
    "status": false,
    "type": "internal",
    "signUpDate": 1581397765728,
    "location": "Moscow",
    "company": "Nike",
    "name": "Mr. Serhii Movchan4",
    "id": "1123"
  },
  {
    "markup": "-",
    "status": false,
    "type": "internal",
    "signUpDate": 1581397765728,
    "location": "Moscow",
    "company": "Nike",
    "name": "Mr. Serhii Movchan5",
    "id": "1134"
  },
  {
    "markup": "-",
    "status": false,
    "type": "internal",
    "signUpDate": 1581397765728,
    "location": "Moscow",
    "company": "Nike",
    "name": "Mr. Serhii Movchan6",
    "id": "199"
  },
  {
    "markup": "-",
    "status": false,
    "type": "internal",
    "signUpDate": 1581397765728,
    "location": "Moscow",
    "company": "Nike",
    "name": "Mr. Serhii Movchan7",
    "id": "188"
  },
  {
    "markup": "-",
    "status": false,
    "type": "internal",
    "signUpDate": 1581397765728,
    "location": "Moscow",
    "company": "Nike",
    "name": "Mr. Serhii Movchan8",
    "id": "177"
  },
  {
    "markup": "-",
    "status": false,
    "type": "internal",
    "signUpDate": 1581397765728,
    "location": "Moscow",
    "company": "Nike",
    "name": "Mr. Serhii Movchan9",
    "id": "166"
  },
  {
    "markup": "-",
    "status": false,
    "type": "internal",
    "signUpDate": 1581397765728,
    "location": "Moscow",
    "company": "Nike",
    "name": "Mr. Serhii Movchan10",
    "id": "155"
  },
  {
    "markup": "-",
    "status": false,
    "type": "internal",
    "signUpDate": 1581397765728,
    "location": "Moscow",
    "company": "Nike",
    "name": "Mr. Serhii Movchan11",
    "id": "144"
  },
  {
    "markup": "-",
    "status": false,
    "type": "internal",
    "signUpDate": 1581397765728,
    "location": "Moscow",
    "company": "Nike",
    "name": "Mr. Serhii Movchan12",
    "id": "133"
  },
  {
    "markup": "-",
    "status": false,
    "type": "internal",
    "signUpDate": 1581397765728,
    "location": "Moscow",
    "company": "Nike",
    "name": "Mr. Serhii Movchan13",
    "id": "122"
  },
  {
    "markup": "-",
    "status": false,
    "type": "internal",
    "signUpDate": 1581397765728,
    "location": "Moscow",
    "company": "Nike",
    "name": "Mr. Serhii Movchan14",
    "id": "111"
  },
  {
    "markup": "-",
    "status": false,
    "type": "internal",
    "signUpDate": 1581397765728,
    "location": "Moscow",
    "company": "Nike",
    "name": "Mr. Serhii Movchan15",
    "id": "100"
  },
  {
    "markup": "-",
    "status": false,
    "type": "internal",
    "signUpDate": 1581397765728,
    "location": "Moscow",
    "company": "Nike",
    "name": "Mr. Serhii Movchan16",
    "id": "19"
  },
  {
    "markup": "-",
    "status": false,
    "type": "internal",
    "signUpDate": 1581397765728,
    "location": "Moscow",
    "company": "Nike",
    "name": "Mr. Serhii Movchan17",
    "id": "18"
  },
  {
    "markup": "-",
    "status": false,
    "type": "internal",
    "signUpDate": 1581397765728,
    "location": "Moscow",
    "company": "Nike",
    "name": "Mr. Serhii Movchan18",
    "id": "17"
  },
  {
    "markup": "-",
    "status": false,
    "type": "internal",
    "signUpDate": 1581397765728,
    "location": "Moscow",
    "company": "Nike",
    "name": "Mr. Serhii Movchan19",
    "id": "16"
  },
  {
    "markup": "-",
    "status": false,
    "type": "internal",
    "signUpDate": 1581397765728,
    "location": "Moscow",
    "company": "Nike",
    "name": "Mr. Serhii Movchan20",
    "id": "15"
  },
  {
    "markup": "-",
    "status": false,
    "type": "internal",
    "signUpDate": 1581397765728,
    "location": "Moscow",
    "company": "Nike",
    "name": "Mr. Serhii Movchan21",
    "id": "14"
  },
  {
    "markup": "-",
    "status": false,
    "type": "internal",
    "signUpDate": 1581397765728,
    "location": "Moscow",
    "company": "Nike",
    "name": "Mr. Serhii Movchan22",
    "id": "11"
  },
  {
    "markup": "-",
    "status": false,
    "type": "internal",
    "signUpDate": 1581397765728,
    "location": "Moscow",
    "company": "Nike",
    "name": "Mr. Serhii Movchan23",
    "id": "12"
  },
  {
    "markup": "-",
    "status": false,
    "type": "internal",
    "signUpDate": 1581397765728,
    "location": "Moscow",
    "company": "Nike",
    "name": "Mr. Serhii Movchan24",
    "id": "13"
  }
]
